{
    "Skirt of the Blazing Superiority": "9245958",
    "Armor of the Drake": "1550409",
    "Inscribed Armor of the Drake": "2004441",
    "Shield of the Drake": "1550498",
    "Inscribed Shield of the Drake": "2007160",
    "Crimson Wyvern Shoulders": "1550449",
    "Inscribed Crimson Wyvern Shoulders": "2010496",
    "Crimson Wyvern Sword": "1550431",
    "Inscribed Crimson Wyvern Sword": "2010442",
    "Sword of the Drake": "1551271",
    "Inscribed Sword of the Drake": "2031728",
    "Crimson Wyvern Skirt": "1550432",
    "Inscribed Crimson Wyvern Skirt": "4232219",
    "Crimson Wyvern Bracers": "1550996",
    "Inscribed Crimson Wyvern Bracers": "4176575",
    "Cape of the Drake": "1551254",
    "Inscribed Cape of the Drake": "4856343",
    "Crimson Wyvern Shield": "1550427",
    "Inscribed Crimson Wyvern Shield": "2023437",
    "Bracers of the Drake": "1550422",
    "Inscribed Bracers of the Drake": "2310506",
    "Helmet of the Drake": "1550459",
    "Inscribed Helmet of the Drake": "2007172"
}