{
    "Inscribed%20Chimes of the Temple Weapon": "176272736",
    "Inscribed%20Headdress of the Loyal Fold": "176111398",
    "Inscribed%20Headpiece of the Deadly Nightshade": "2075273",
    "Inscribed%20Seclusions of the Void": "176400907",
    "Inscribed%20Wings of the Fluttering Amethyst": "25886193",
    "Inscribed%20Armor of the Onyx Lotus": "49359021",
    "Inscribed%20Hair of the Onyx Lotus": "49358992",
    "Inscribed%20Whispering Dead Mantle": "2591929",
    "Inscribed%20Faction of the Feather - Armor": "176329672",
    "Inscribed%20Whispering Dead Mask": "2351212",
    "Inscribed%20Faction of the Feather - Head": "176329677",
    "Inscribed%20Artist of the Astral Summer - Head": "176352307",
    "Inscribed%20Faction of the Feather - Shoulder": "176329685",
    "Inscribed%20Sash of the Third Insight": "2161191",
    "Inscribed%20Focal Resonance": "64116573",
    "Inscribed%20Faction of the Feather - Weapon": "176329675",
    "Inscribed%20Dreaded Bravo's Cape": "2792009",
    "Inscribed%20Tail of the Secret Order": "6215056",
    "Inscribed%20Guards of the Hidden Flower": "20876716",
    "Inscribed%20Dreaded Bravo's Scarf": "2366689",
    "Inscribed%20Redmoon Assassin's Secret Wraps": "2113296",
    "Inscribed%20Redmoon Assassin's Secret Armor": "2167914",
    "Inscribed%20Golden Seclusions of the Void": "176400870",
    "Inscribed%20Garb of the Deadly Nightshade": "2792643",
    "Inscribed%20Mask of the Third Insight": "2030331",
    "Inscribed%20Sleeves of the Hidden Flower": "20876726",
    "Inscribed%20Whispering Dead Armor": "2803988",
    "Inscribed%20Artist of the Astral Summer - Shoulder": "176352309",
    "Inscribed%20Veil of the Hidden Flower": "20878126",
    "Inscribed%20Faceless Destiny Shoulder": "176319328",
    "Inscribed%20Dress of the Onyx Lotus": "49358998",
    "Inscribed%20Epitaphic Bonds Armor": "15106861",
    "Inscribed%20Chimes of the Temple Armor": "176272734",
    "Inscribed%20Epitaphic Bonds Shoulders": "15106872",
    "Inscribed%20Faceless Destiny Armor": "176319327",
    "Inscribed%20Heirloom of the Temple Priestess": "2321339",
    "Inscribed%20Blades of the Loyal Fold": "176111230",
    "Inscribed%20Mantle of the Whispered Bond": "176083040",
    "Inscribed%20Faceless Destiny Weapon": "176319329",
    "Inscribed%20Pauldrons of the Timekeeper": "145482062",
    "Inscribed%20Dreaded Bravo's Guise": "2478090",
    "Inscribed%20Guards of the Psion Inquisitor": "175852236",
    "Inscribed%20Epitaphic Bonds Hair": "15106907",
    "Inscribed%20Charming Assassin Curls": "7475891",
    "Inscribed%20Brooch of the Third Insight": "2161212",
    "Inscribed%20Armor of the Timekeeper": "145475412",
    "Inscribed%20Chimes of the Temple Shoulder": "176272733",
    "Inscribed%20Headpiece of the Wuxia": "140175954",
    "Inscribed%20Brooch of the Fluttering Amethyst": "25922106",
    "Inscribed%20Skirt of the Fluttering Amethyst": "25886201",
    "Inscribed%20Hood of the Concealed Raven": "91654518",
    "Inscribed%20Scarf of the Deadly Nightshade": "2254077",
    "Inscribed%20Style of the Occult Protector": "2282900",
    "Inscribed%20Chimes of the Temple Head": "176272735",
    "Inscribed%20Spaulders of Wuxia": "143143933",
    "Inscribed%20Armor of the Wuxia": "143143934",
    "Inscribed%20Whisper at the Temple Gates - Shoulder": "176414679",
    "Inscribed%20Artist of the Astral Summer - Armor": "176352269",
    "Inscribed%20Whisper at the Temple Gates - Head": "176414658",
    "Inscribed%20Whisper at the Temple Gates - Armor": "176414678",
    "Inscribed%20Spaulders of the Psion Inquisitor": "175852235",
    "Inscribed%20Halter of the Clandestine Trail": "92055787",
    "Inscribed%20Whisper at the Temple Gates - Weapon": "176414669",
    "Inscribed%20Seclusions of the Void of the Crimson Witness": "176407971",
    "Inscribed%20Style of the Clandestine Trail": "91732564",
    "Inscribed%20Feathers of the Concealed Raven": "91654519",
    "Inscribed%20Faceless Destiny Head": "176319131",
    "Inscribed%20Armor of the Loyal Fold": "176111397",
    "Inscribed%20Style of the Timekeeper": "145698518",
    "Inscribed%20Complete Guards of the Psion Inquisitor": "176121375",
    "Inscribed%20Complete Spaulders of the Psion Inquisitor": "176102795",
    "Inscribed%20Pauldrons of the Loyal Fold": "176111342",
    "Inscribed%20Mantle of the Concealed Raven": "91654520",
    "Inscribed%20Plume of the Clandestine Trail": "92052350",
    "Faction of the Feather - Weapon": "176329576",
    "Inscribed Faction of the Feather - Weapon": "176329675",
    "Faction of the Feather - Shoulder": "176329582",
    "Inscribed Faction of the Feather - Shoulder": "176329685",
    "Faction of the Feather - Armor": "176329584",
    "Inscribed Faction of the Feather - Armor": "176329672",
    "Seclusions of the Void": "176400841",
    "Inscribed Seclusions of the Void": "176400907",
    "Artist of the Astral Summer - Head": "176352130",
    "Inscribed Artist of the Astral Summer - Head": "176352307",
    "Redmoon Assassin's Secret Headwear": "2007535",
    "Inscribed Redmoon Assassin's Secret Headwear": "2542595",
    "Tail of the Secret Order": "6141793",
    "Inscribed Tail of the Secret Order": "6215056",
    "Artist of the Astral Summer - Armor": "176352154",
    "Inscribed Artist of the Astral Summer - Armor": "176352269",
    "Hair of the Onyx Lotus": "49358995",
    "Inscribed Hair of the Onyx Lotus": "49358992"
}